src/__init__.py
src/core.py
EzScanner-1.3.1.dist-info/LICENSE.md
EzScanner-1.3.1.dist-info/METADATA
EzScanner-1.3.1.dist-info/WHEEL
EzScanner-1.3.1.dist-info/entry_points.txt
EzScanner-1.3.1.dist-info/top_level.txt
EzScanner-1.3.1.dist-info/RECORD
